LICENSE
README.md
aiwaf_flask/AIWAF_SETTINGS_EXAMPLE.py
aiwaf_flask/AIWAF_SETTINGS_GUIDE.py
aiwaf_flask/__init__.py
aiwaf_flask/anomaly_middleware.py
aiwaf_flask/apps.py
aiwaf_flask/auto_config.py
aiwaf_flask/blacklist_manager.py
aiwaf_flask/cli.py
aiwaf_flask/db_models.py
aiwaf_flask/decorators.py
aiwaf_flask/example_app.py
aiwaf_flask/example_csv_app.py
aiwaf_flask/example_full_app.py
aiwaf_flask/exemption_decorators.py
aiwaf_flask/flask_integration.py
aiwaf_flask/geo_block_middleware.py
aiwaf_flask/geoip.py
aiwaf_flask/geolock/ipinfo_lite.mmdb
aiwaf_flask/header_validation_middleware.py
aiwaf_flask/honeypot_timing_middleware.py
aiwaf_flask/ip_and_keyword_block_middleware.py
aiwaf_flask/logging_middleware.py
aiwaf_flask/middleware.py
aiwaf_flask/middleware_logger.py
aiwaf_flask/models.py
aiwaf_flask/rate_limit_middleware.py
aiwaf_flask/resources/__init__.py
aiwaf_flask/resources/model.pkl
aiwaf_flask/rust_backend.py
aiwaf_flask/setup.py
aiwaf_flask/storage.py
aiwaf_flask/storage_backup.py
aiwaf_flask/storage_csv.py
aiwaf_flask/test_all_middlewares.py
aiwaf_flask/test_middleware_integration.py
aiwaf_flask/trainer.py
aiwaf_flask/utils.py
aiwaf_flask/uuid_tamper_middleware.py
aiwaf_flask-0.1.5.dist-info/METADATA
aiwaf_flask-0.1.5.dist-info/WHEEL
aiwaf_flask-0.1.5.dist-info/entry_points.txt
aiwaf_flask-0.1.5.dist-info/licenses/LICENSE
aiwaf_rust/__init__.py
aiwaf_rust/aiwaf_rust.cpython-39-x86_64-linux-gnu.so
aiwaf_flask-0.1.5.dist-info/RECORD
