Metadata-Version: 2.4
Name: aiwaf-flask
Version: 0.1.5
Classifier: Development Status :: 4 - Beta
Classifier: Intended Audience :: Developers
Classifier: License :: OSI Approved :: MIT License
Classifier: Operating System :: OS Independent
Classifier: Programming Language :: Python :: 3
Classifier: Programming Language :: Python :: 3.8
Classifier: Programming Language :: Python :: 3.9
Classifier: Programming Language :: Python :: 3.10
Classifier: Programming Language :: Python :: 3.11
Classifier: Programming Language :: Python :: 3.12
Classifier: Framework :: Flask
Classifier: Topic :: Internet :: WWW/HTTP :: HTTP Servers
Classifier: Topic :: Security
Classifier: Topic :: Software Development :: Libraries :: Python Modules
Requires-Dist: flask>=2.0.0
Requires-Dist: flask-sqlalchemy>=3.0.0
Requires-Dist: geoip2>=4.0.0
Requires-Dist: numpy>=1.20.0 ; extra == 'ai'
Requires-Dist: pandas>=1.5.0 ; extra == 'ai'
Requires-Dist: scikit-learn>=1.0.0 ; extra == 'ai'
Requires-Dist: joblib>=1.0.0 ; extra == 'ai'
Requires-Dist: numpy>=1.20.0 ; extra == 'all'
Requires-Dist: pandas>=1.5.0 ; extra == 'all'
Requires-Dist: scikit-learn>=1.0.0 ; extra == 'all'
Requires-Dist: geoip2>=4.0.0 ; extra == 'all'
Requires-Dist: pytest>=7.0.0 ; extra == 'all'
Requires-Dist: flask-testing>=0.8.1 ; extra == 'all'
Requires-Dist: pytest-cov>=4.0.0 ; extra == 'all'
Requires-Dist: joblib>=1.0.0 ; extra == 'all'
Requires-Dist: pytest>=7.0.0 ; extra == 'dev'
Requires-Dist: flask-testing>=0.8.1 ; extra == 'dev'
Requires-Dist: pytest-cov>=4.0.0 ; extra == 'dev'
Requires-Dist: geoip2>=4.0.0 ; extra == 'geo'
Provides-Extra: ai
Provides-Extra: all
Provides-Extra: dev
Provides-Extra: geo
License-File: LICENSE
Summary: Advanced AI-powered Web Application Firewall for Flask with intelligent threat detection, rate limiting, IP blocking, and real-time protection against web attacks
Keywords: flask,security,firewall,web,protection,middleware,rate-limiting,ip-blocking,ddos,waf
Author-email: Aayush Gauba <gauba.aayush@gmail.com>
Maintainer-email: Aayush Gauba <gauba.aayush@gmail.com>
License: MIT
Requires-Python: >=3.8
Project-URL: Bug Tracker, https://github.com/aayushgauba/aiwaf_flask/issues
Project-URL: Documentation, https://github.com/aayushgauba/aiwaf_flask#readme
Project-URL: Homepage, https://github.com/aayushgauba/aiwaf_flask
Project-URL: Repository, https://github.com/aayushgauba/aiwaf_flask.git
